material/404.html
material/__init__.py
material/base.html
material/main.html
material/mkdocs_theme.yml
material/assets/fonts/font-awesome.css
material/assets/fonts/material-icons.css
material/assets/fonts/specimen/FontAwesome.ttf
material/assets/fonts/specimen/FontAwesome.woff
material/assets/fonts/specimen/FontAwesome.woff2
material/assets/fonts/specimen/MaterialIcons-Regular.ttf
material/assets/fonts/specimen/MaterialIcons-Regular.woff
material/assets/fonts/specimen/MaterialIcons-Regular.woff2
material/assets/images/favicon.png
material/assets/images/icons/bitbucket.1b09e088.svg
material/assets/images/icons/github.f0b8504a.svg
material/assets/images/icons/gitlab.6dd19c00.svg
material/assets/javascripts/application.63928fc3.js
material/assets/javascripts/modernizr.74668098.js
material/assets/javascripts/lunr/lunr.da.js
material/assets/javascripts/lunr/lunr.de.js
material/assets/javascripts/lunr/lunr.du.js
material/assets/javascripts/lunr/lunr.es.js
material/assets/javascripts/lunr/lunr.fi.js
material/assets/javascripts/lunr/lunr.fr.js
material/assets/javascripts/lunr/lunr.hu.js
material/assets/javascripts/lunr/lunr.it.js
material/assets/javascripts/lunr/lunr.ja.js
material/assets/javascripts/lunr/lunr.jp.js
material/assets/javascripts/lunr/lunr.multi.js
material/assets/javascripts/lunr/lunr.nl.js
material/assets/javascripts/lunr/lunr.no.js
material/assets/javascripts/lunr/lunr.pt.js
material/assets/javascripts/lunr/lunr.ro.js
material/assets/javascripts/lunr/lunr.ru.js
material/assets/javascripts/lunr/lunr.stemmer.support.js
material/assets/javascripts/lunr/lunr.sv.js
material/assets/javascripts/lunr/lunr.th.js
material/assets/javascripts/lunr/lunr.tr.js
material/assets/javascripts/lunr/tinyseg.js
material/assets/javascripts/lunr/wordcut.js
material/assets/stylesheets/application-palette.4f3b7450.css
material/assets/stylesheets/application.50f26899.css
material/partials/footer.html
material/partials/header.html
material/partials/hero.html
mkdocs_rokubun-4.4.2.dist-info/LICENSE
mkdocs_rokubun-4.4.2.dist-info/METADATA
mkdocs_rokubun-4.4.2.dist-info/WHEEL
mkdocs_rokubun-4.4.2.dist-info/entry_points.txt
mkdocs_rokubun-4.4.2.dist-info/top_level.txt
mkdocs_rokubun-4.4.2.dist-info/RECORD
