Metadata-Version: 2.1
Name: mkdocs-rokubun
Version: 4.4.2
Summary: A fork of Material Design theme for MkDocs for Rokubun
Home-page: https://github.com/rokubun/mkdocs-rokubun
Author: Martin Donath
Author-email: martin.donath@squidfunk.com
License: MIT
Keywords: mkdocs,documentation,theme
Platform: UNKNOWN
Classifier: Development Status :: 5 - Production/Stable
Classifier: License :: OSI Approved :: MIT License
Classifier: Programming Language :: JavaScript
Classifier: Programming Language :: Python
Classifier: Topic :: Documentation
Classifier: Topic :: Text Processing :: Markup :: HTML
Requires-Dist: mkdocs (>=1)
Requires-Dist: mkdocs-minify-plugin (>=0.2)
Requires-Dist: Pygments (>=2.2)
Requires-Dist: pymdown-extensions (>=4.11)
